pylocalytics/__init__.py
pylocalytics-1.0.dist-info/METADATA
pylocalytics-1.0.dist-info/RECORD
pylocalytics-1.0.dist-info/WHEEL
pylocalytics-1.0.dist-info/top_level.txt
