Metadata-Version: 2.1
Name: pylocalytics
Version: 1.0
Summary: Python API Client for Localytics Raw Data Export and Audience Export
Home-page: https://github.com/zhilevan/pylocalytics
Author: Zhilevan Ibra
Author-email: zhilevan@gmail.com
License: MIT
Platform: UNKNOWN
